LICENSE
README.md
setup.py
PhoenixScanner/__init__.py
PhoenixScanner/gbancheck.py
pySeven.egg-info/PKG-INFO
pySeven.egg-info/SOURCES.txt
pySeven.egg-info/dependency_links.txt
pySeven.egg-info/requires.txt
pySeven.egg-info/top_level.txt
test/test_gban_check.py