Metadata-Version: 2.1
Name: pySeven
Version: 1.0.2
Summary: A API bassed telegram gban scanner.
Home-page: https://github.com/SOME-1HING/PhoenixScanner
Author: SOME1HING
Author-email: yashprakash2005@gmail.com
License: GNU General Public License v3.0
Keywords: telegram,phoenix,bot,api,gban,scan
Classifier: Framework :: AsyncIO
Classifier: Development Status :: 3 - Alpha
Classifier: Intended Audience :: Developers
Classifier: License :: OSI Approved :: GNU General Public License v2 or later (GPLv2+)
Classifier: Natural Language :: English
Classifier: Operating System :: OS Independent
Classifier: Programming Language :: Python :: 3.7
Classifier: Programming Language :: Python :: 3.8
Classifier: Programming Language :: Python :: 3.9
Classifier: Programming Language :: Python :: 3.10
Classifier: Topic :: Internet :: WWW/HTTP
Classifier: Topic :: Software Development :: Libraries
Classifier: Topic :: Software Development :: Build Tools
License-File: LICENSE
